admin/__init__.py
admin/unrelated_inlines/__init__.py
admin/unrelated_inlines/core.py
admin/unrelated_inlines/forms.py
decorators/__init__.py
decorators/formatting.py
export_import/__init__.py
export_import/export.py
mixins/__init__.py
mixins/django_admin.py
mixins/models.py
mixins/queries.py
corfmanntools-1.0.3.dist-info/LICENSE.md
corfmanntools-1.0.3.dist-info/METADATA
corfmanntools-1.0.3.dist-info/WHEEL
corfmanntools-1.0.3.dist-info/top_level.txt
corfmanntools-1.0.3.dist-info/RECORD
